{"skills": {"Overall": ["-1", "638", "1667943"], "Attack": ["-1", "44", "60636"], "Defense": ["-1", "32", "18175"], "Strength": ["-1", "31", "15345"], "Hitpoints": ["-1", "28", "11610"], "Ranged": ["-1", "2", "92"], "Prayer": ["-1", "30", "14733"], "Magic": ["-1", "31", "14859"], "Cooking": ["-1", "36", "26910"], "Woodcutting": ["-1", "51", "120487"], "Fletching": ["-1", "7", "665"], "Fishing": ["-1", "38", "30675"], "Firemaking": ["698842", "72", "960990"], "Crafting": ["-1", "26", "8858"], "Smithing": ["-1", "1", "18"], "Mining": ["-1", "18", "3875"], "Herblore": ["1761382", "18", "3567"], "Agility": ["1396626", "50", "111018"], "Thieving": ["697410", "59", "250405"], "Slayer": ["-1", "13", "2000"], "Farming": ["1190745", "27", "9777"], "Runecrafting": ["-1", "1", "0"], "Hunter": ["1328840", "12", "1800"], "Construction": ["1682615", "11", "1448"]}, "bosses": {"Bounty Hunter - Hunter": ["-1", "-1"], "Bounty Hunter - Rogue": ["-1", "-1"], "Clue Scrolls (All)": ["-1", "-1"], "Clue Scrolls (Beginner)": ["854402", "4"], "Clue Scrolls (Easy)": ["669789", "2"], "Clue Scrolls (Medium)": ["1262314", "1"], "Clue Scrolls (Hard)": ["1075107", "1"], "Clue Scrolls (Elite)": ["-1", "-1"], "Clue Scrolls (Master)": ["-1", "-1"], "LMS - Rank": ["-1", "-1"], "Soul Wars Zeal": ["-1", "-1"], "Abyssal Sire": ["-1", "-1"], "Alchemical Hydra": ["-1", "-1"], "Barrows Chests": ["-1", "-1"], "Bryophyta": ["-1", "-1"], "Callisto": ["-1", "-1"], "Cerberus": ["-1", "-1"], "Chambers of Xeric": ["-1", "-1"], "Chambers of Xeric: Challenge Mode": ["-1", "-1"], "Chaos Elemental": ["-1", "-1"], "Chaos Fanatic": ["-1", "-1"], "Commander Zilyana": ["-1", "-1"], "Corporeal Beast": ["-1", "-1"], "Crazy Archaeologist": ["-1", "-1"], "Dagannoth Prime": ["-1", "-1"], "Dagannoth Rex": ["-1", "-1"], "Dagannoth Supreme": ["-1", "-1"], "Deranged Archaeologist": ["-1", "-1"], "General Draardor": ["-1", "-1"], "Giant Mole": ["-1", "-1"], "Grotesque Guardians": ["-1", "-1"], "Hespori": ["-1", "-1"], "Kalphite Queen": ["-1", "-1"], "King Black Dragon": ["-1", "-1"], "Kraken": ["-1", "-1"], "Kree'Arra": ["-1", "-1"], "K'ril Tsutsaroth": ["-1", "-1"], "Mimic": ["-1", "-1"], "Nightmare": ["-1", "-1"], "Phosani's Nightmare": ["-1", "-1"], "Orbor": ["-1", "-1"], "Sarachnis": ["-1", "-1"], "Scorpia": ["-1", "-1"], "Skotizo": ["-1", "-1"], "Tempoross": ["-1", "-1"], "The Gauntlet": ["-1", "-1"], "The Corrupted Gauntlet": ["-1", "-1"], "Theatre of Blood": ["-1", "-1"], "Theatre of Blood: Hard Mode": ["-1", "-1"], "Thermonuclear Smoke Devil": ["-1", "-1"], "TzKal-Zuk": ["-1", "-1"], "TzKal-Jad": ["-1", "-1"], "Vet'ion": ["-1", "-1"], "Vorkath": ["-1", "-1"], "Wintertodt": ["-1", "-1"], "Zalcano": ["-1", "-1"], "Zulrah": ["-1", "-1"]}, "character": "GroupIronMom"}